ipyhealth/__init__.py
ipyhealth/cli.py
ipyhealth/ipyhealth.py
ipyhealth/parser.py
ipyhealth/templates/__init__.py
ipyhealth/templates/activity_format.json
ipyhealth-0.1.2.dist-info/AUTHORS.rst
ipyhealth-0.1.2.dist-info/LICENSE
ipyhealth-0.1.2.dist-info/METADATA
ipyhealth-0.1.2.dist-info/WHEEL
ipyhealth-0.1.2.dist-info/entry_points.txt
ipyhealth-0.1.2.dist-info/top_level.txt
ipyhealth-0.1.2.dist-info/RECORD
