Metadata-Version: 2.1
Name: ipyhealth
Version: 0.1.2
Summary: A library to parse, wrangle and plot Apple Health data.
Home-page: https://github.com/mereldawu/ipyhealth
Author: Merelda Wu
Author-email: merelda@melio.co.za
License: MIT license
Keywords: ipyhealth
Platform: UNKNOWN
Classifier: Development Status :: 2 - Pre-Alpha
Classifier: Intended Audience :: Developers
Classifier: License :: OSI Approved :: MIT License
Classifier: Natural Language :: English
Classifier: Programming Language :: Python :: 3
Classifier: Programming Language :: Python :: 3.5
Classifier: Programming Language :: Python :: 3.6
Classifier: Programming Language :: Python :: 3.7
Classifier: Programming Language :: Python :: 3.8
Requires-Python: >=3.5
Requires-Dist: Click (>=7.0)
Requires-Dist: pandas (>=1.0.0)
Requires-Dist: tqdm (>=4.46.0)
Requires-Dist: inflection (>=0.4.0)
Requires-Dist: gpxpy (>=1.4.0)
Requires-Dist: geopy (>=1.22.0)
Requires-Dist: importlib-resources ; python_version < "3.7"
